aioadmin/__init__.py
aioadmin/adapter.py
aioadmin/exceptions.py
aioadmin/permissions.py
aioadmin/record.py
aioadmin/aiogram/middleware.py
aioadmin/aiogram/router.py
aioadmin/aiogram/handlers/create.py
aioadmin/aiogram/handlers/delete.py
aioadmin/aiogram/handlers/menu.py
aioadmin/aiogram/handlers/start.py
aioadmin/aiogram/handlers/states.py
aioadmin/aiogram/handlers/update.py
aioadmin/orm/sqlalchemy.py
aioadmin-0.0.1.dist-info/licenses/LICENSE
aioadmin-0.0.1.dist-info/METADATA
aioadmin-0.0.1.dist-info/WHEEL
aioadmin-0.0.1.dist-info/top_level.txt
aioadmin-0.0.1.dist-info/RECORD
