Metadata-Version: 2.4
Name: aioadmin
Version: 0.0.1
Summary: Admin panel for aiogram
Author-email: AliakseiYafremau <aleksey.yafremau@gmail.com>
Requires-Python: >=3.10
License-File: LICENSE
Requires-Dist: aiogram==3.22.0
Requires-Dist: aiogram-dialog>=2.4.0
Requires-Dist: sqlalchemy==2.0.44
Dynamic: license-file
